GraphModels/BellmanAlgorithm.py
GraphModels/DijkstraAlgorithm.py
GraphModels/PertAlgorithm.py
GraphModels/__init__.py
GraphModels/cli.py
GraphModels-0.1.0.dist-info/METADATA
GraphModels-0.1.0.dist-info/WHEEL
GraphModels-0.1.0.dist-info/top_level.txt
GraphModels-0.1.0.dist-info/RECORD
