Metadata-Version: 2.1
Name: GraphModels
Version: 0.1.0
Summary: GraphModels: A package containing algorithms for pathfinding, scheduling, and maximum flow problems
Author: Alikacem Faycal
Author-email: faycal213.dz@gmail.com
Project-URL: Source, https://github.com/Faycal214/Graph-models
Classifier: Development Status :: 3 - Alpha
Classifier: Intended Audience :: Science/Research
Classifier: Intended Audience :: Developers
Classifier: Programming Language :: Python :: 3.11
Classifier: Programming Language :: Python :: 3.12
Classifier: Topic :: Utilities
Requires-Python: >= 3.10, <3.13
Requires-Dist: math
Requires-Dist: random
Requires-Dist: matplotlib
Requires-Dist: networkx
